registry/__init__.py
registry/auth/__init__.py
registry/auth/bearer.py
registry/auth/exceptions.py
registry/auth/middleware.py
registry/aws_lambda/__init__.py
registry/aws_lambda/registry_lambda.py
registry/cli/credential_helper.py
registry/cli/gen_docs.py
registry/cli/iam_permissions_manager.py
registry/cli/iam_token_fetcher.py
registry/cli/install_terraform_credential_helper.py
registry/config.py
registry/models.py
registry/routes.py
lambda_terraform_module_registry-0.2.5.dist-info/METADATA
lambda_terraform_module_registry-0.2.5.dist-info/WHEEL
lambda_terraform_module_registry-0.2.5.dist-info/entry_points.txt
lambda_terraform_module_registry-0.2.5.dist-info/RECORD
